antlr4_grun/__init__.py
antlr4_grun/cli.py
antlr4_grun/lib.py
antlr4_grun/util.py
antlr4_grun-0.4.0.dist-info/entry_points.txt
antlr4_grun-0.4.0.dist-info/LICENSE
antlr4_grun-0.4.0.dist-info/WHEEL
antlr4_grun-0.4.0.dist-info/METADATA
antlr4_grun-0.4.0.dist-info/RECORD
